<?xml version="1.0" encoding="UTF-8" ?>
<!DOCTYPE mapper PUBLIC "-//mybatis.org//DTD Mapper 3.0//EN" "http://mybatis.org/dtd/mybatis-3-mapper.dtd" >
<mapper namespace="com.chinasofti.rcloud.dao.AuditLogEntityMapper" >
  <resultMap id="BaseResultMap" type="com.chinasofti.rcloud.domain.AuditLogEntity" >
    <!--
      WARNING - @mbggenerated
      This element is automatically generated by MyBatis Generator, do not modify.
      This element was generated on Mon Jan 19 10:09:58 CST 2015.
    -->
    <id column="audit_log_id" property="auditLogId" jdbcType="VARCHAR" />
    <result column="user_id" property="userId" jdbcType="VARCHAR" />
    <result column="service_id" property="serviceId" jdbcType="VARCHAR" />
    <result column="user_type" property="userType" jdbcType="INTEGER" />
    <result column="role_code" property="roleCode" jdbcType="VARCHAR" />
    <result column="create_date" property="createDate" jdbcType="TIMESTAMP" />
    <result column="operation" property="operation" jdbcType="VARCHAR" />
    <result column="remarks" property="remarks" jdbcType="VARCHAR" />
    <result column="description" property="description" jdbcType="VARCHAR" />
  </resultMap>
  <sql id="Example_Where_Clause" >
    <!--
      WARNING - @mbggenerated
      This element is automatically generated by MyBatis Generator, do not modify.
      This element was generated on Mon Jan 19 10:09:58 CST 2015.
    -->
    <where >
      <foreach collection="oredCriteria" item="criteria" separator="or" >
        <if test="criteria.valid" >
          <trim prefix="(" suffix=")" prefixOverrides="and" >
            <foreach collection="criteria.criteria" item="criterion" >
              <choose >
                <when test="criterion.noValue" >
                  and ${criterion.condition}
                </when>
                <when test="criterion.singleValue" >
                  and ${criterion.condition} #{criterion.value}
                </when>
                <when test="criterion.betweenValue" >
                  and ${criterion.condition} #{criterion.value} and #{criterion.secondValue}
                </when>
                <when test="criterion.listValue" >
                  and ${criterion.condition}
                  <foreach collection="criterion.value" item="listItem" open="(" close=")" separator="," >
                    #{listItem}
                  </foreach>
                </when>
              </choose>
            </foreach>
          </trim>
        </if>
      </foreach>
    </where>
  </sql>
  <sql id="Update_By_Example_Where_Clause" >
    <!--
      WARNING - @mbggenerated
      This element is automatically generated by MyBatis Generator, do not modify.
      This element was generated on Mon Jan 19 10:09:58 CST 2015.
    -->
    <where >
      <foreach collection="example.oredCriteria" item="criteria" separator="or" >
        <if test="criteria.valid" >
          <trim prefix="(" suffix=")" prefixOverrides="and" >
            <foreach collection="criteria.criteria" item="criterion" >
              <choose >
                <when test="criterion.noValue" >
                  and ${criterion.condition}
                </when>
                <when test="criterion.singleValue" >
                  and ${criterion.condition} #{criterion.value}
                </when>
                <when test="criterion.betweenValue" >
                  and ${criterion.condition} #{criterion.value} and #{criterion.secondValue}
                </when>
                <when test="criterion.listValue" >
                  and ${criterion.condition}
                  <foreach collection="criterion.value" item="listItem" open="(" close=")" separator="," >
                    #{listItem}
                  </foreach>
                </when>
              </choose>
            </foreach>
          </trim>
        </if>
      </foreach>
    </where>
  </sql>
  <sql id="Base_Column_List" >
    <!--
      WARNING - @mbggenerated
      This element is automatically generated by MyBatis Generator, do not modify.
      This element was generated on Mon Jan 19 10:09:58 CST 2015.
    -->
    audit_log_id, user_id, service_id, user_type, role_code, create_date, operation, 
    remarks, description
  </sql>
  <select id="selectByExample" resultMap="BaseResultMap" parameterType="com.chinasofti.rcloud.domain.AuditLogEntityExample" >
    <!--
      WARNING - @mbggenerated
      This element is automatically generated by MyBatis Generator, do not modify.
      This element was generated on Mon Jan 19 10:09:58 CST 2015.
    -->
    select
    <if test="distinct" >
      distinct
    </if>
    <include refid="Base_Column_List" />
    from boss_audit_log
    <if test="_parameter != null" >
      <include refid="Example_Where_Clause" />
    </if>
    <if test="orderByClause != null" >
      order by ${orderByClause}
    </if>
  </select>
  <select id="selectByPrimaryKey" resultMap="BaseResultMap" parameterType="java.lang.String" >
    <!--
      WARNING - @mbggenerated
      This element is automatically generated by MyBatis Generator, do not modify.
      This element was generated on Mon Jan 19 10:09:58 CST 2015.
    -->
    select 
    <include refid="Base_Column_List" />
    from boss_audit_log
    where audit_log_id = #{auditLogId,jdbcType=VARCHAR}
  </select>
  <delete id="deleteByPrimaryKey" parameterType="java.lang.String" >
    <!--
      WARNING - @mbggenerated
      This element is automatically generated by MyBatis Generator, do not modify.
      This element was generated on Mon Jan 19 10:09:58 CST 2015.
    -->
    delete from boss_audit_log
    where audit_log_id = #{auditLogId,jdbcType=VARCHAR}
  </delete>
  <delete id="deleteByExample" parameterType="com.chinasofti.rcloud.domain.AuditLogEntityExample" >
    <!--
      WARNING - @mbggenerated
      This element is automatically generated by MyBatis Generator, do not modify.
      This element was generated on Mon Jan 19 10:09:58 CST 2015.
    -->
    delete from boss_audit_log
    <if test="_parameter != null" >
      <include refid="Example_Where_Clause" />
    </if>
  </delete>
  <insert id="insert" parameterType="com.chinasofti.rcloud.domain.AuditLogEntity" >
    <!--
      WARNING - @mbggenerated
      This element is automatically generated by MyBatis Generator, do not modify.
      This element was generated on Mon Jan 19 10:09:58 CST 2015.
    -->
    insert into boss_audit_log (audit_log_id, user_id, service_id, 
      user_type, role_code, create_date, 
      operation, remarks, description
      )
    values (#{auditLogId,jdbcType=VARCHAR}, #{userId,jdbcType=VARCHAR}, #{serviceId,jdbcType=VARCHAR}, 
      #{userType,jdbcType=INTEGER}, #{roleCode,jdbcType=VARCHAR}, #{createDate,jdbcType=TIMESTAMP}, 
      #{operation,jdbcType=VARCHAR}, #{remarks,jdbcType=VARCHAR}, #{description,jdbcType=VARCHAR}
      )
  </insert>
  <insert id="insertSelective" parameterType="com.chinasofti.rcloud.domain.AuditLogEntity" >
    <!--
      WARNING - @mbggenerated
      This element is automatically generated by MyBatis Generator, do not modify.
      This element was generated on Mon Jan 19 10:09:58 CST 2015.
    -->
    insert into boss_audit_log
    <trim prefix="(" suffix=")" suffixOverrides="," >
      <if test="auditLogId != null" >
        audit_log_id,
      </if>
      <if test="userId != null" >
        user_id,
      </if>
      <if test="serviceId != null" >
        service_id,
      </if>
      <if test="userType != null" >
        user_type,
      </if>
      <if test="roleCode != null" >
        role_code,
      </if>
      <if test="createDate != null" >
        create_date,
      </if>
      <if test="operation != null" >
        operation,
      </if>
      <if test="remarks != null" >
        remarks,
      </if>
      <if test="description != null" >
        description,
      </if>
    </trim>
    <trim prefix="values (" suffix=")" suffixOverrides="," >
      <if test="auditLogId != null" >
        #{auditLogId,jdbcType=VARCHAR},
      </if>
      <if test="userId != null" >
        #{userId,jdbcType=VARCHAR},
      </if>
      <if test="serviceId != null" >
        #{serviceId,jdbcType=VARCHAR},
      </if>
      <if test="userType != null" >
        #{userType,jdbcType=INTEGER},
      </if>
      <if test="roleCode != null" >
        #{roleCode,jdbcType=VARCHAR},
      </if>
      <if test="createDate != null" >
        #{createDate,jdbcType=TIMESTAMP},
      </if>
      <if test="operation != null" >
        #{operation,jdbcType=VARCHAR},
      </if>
      <if test="remarks != null" >
        #{remarks,jdbcType=VARCHAR},
      </if>
      <if test="description != null" >
        #{description,jdbcType=VARCHAR},
      </if>
    </trim>
  </insert>
  <select id="countByExample" parameterType="com.chinasofti.rcloud.domain.AuditLogEntityExample" resultType="java.lang.Integer" >
    <!--
      WARNING - @mbggenerated
      This element is automatically generated by MyBatis Generator, do not modify.
      This element was generated on Mon Jan 19 10:09:58 CST 2015.
    -->
    select count(*) from boss_audit_log
    <if test="_parameter != null" >
      <include refid="Example_Where_Clause" />
    </if>
  </select>
  <update id="updateByExampleSelective" parameterType="map" >
    <!--
      WARNING - @mbggenerated
      This element is automatically generated by MyBatis Generator, do not modify.
      This element was generated on Mon Jan 19 10:09:58 CST 2015.
    -->
    update boss_audit_log
    <set >
      <if test="record.auditLogId != null" >
        audit_log_id = #{record.auditLogId,jdbcType=VARCHAR},
      </if>
      <if test="record.userId != null" >
        user_id = #{record.userId,jdbcType=VARCHAR},
      </if>
      <if test="record.serviceId != null" >
        service_id = #{record.serviceId,jdbcType=VARCHAR},
      </if>
      <if test="record.userType != null" >
        user_type = #{record.userType,jdbcType=INTEGER},
      </if>
      <if test="record.roleCode != null" >
        role_code = #{record.roleCode,jdbcType=VARCHAR},
      </if>
      <if test="record.createDate != null" >
        create_date = #{record.createDate,jdbcType=TIMESTAMP},
      </if>
      <if test="record.operation != null" >
        operation = #{record.operation,jdbcType=VARCHAR},
      </if>
      <if test="record.remarks != null" >
        remarks = #{record.remarks,jdbcType=VARCHAR},
      </if>
      <if test="record.description != null" >
        description = #{record.description,jdbcType=VARCHAR},
      </if>
    </set>
    <if test="_parameter != null" >
      <include refid="Update_By_Example_Where_Clause" />
    </if>
  </update>
  <update id="updateByExample" parameterType="map" >
    <!--
      WARNING - @mbggenerated
      This element is automatically generated by MyBatis Generator, do not modify.
      This element was generated on Mon Jan 19 10:09:58 CST 2015.
    -->
    update boss_audit_log
    set audit_log_id = #{record.auditLogId,jdbcType=VARCHAR},
      user_id = #{record.userId,jdbcType=VARCHAR},
      service_id = #{record.serviceId,jdbcType=VARCHAR},
      user_type = #{record.userType,jdbcType=INTEGER},
      role_code = #{record.roleCode,jdbcType=VARCHAR},
      create_date = #{record.createDate,jdbcType=TIMESTAMP},
      operation = #{record.operation,jdbcType=VARCHAR},
      remarks = #{record.remarks,jdbcType=VARCHAR},
      description = #{record.description,jdbcType=VARCHAR}
    <if test="_parameter != null" >
      <include refid="Update_By_Example_Where_Clause" />
    </if>
  </update>
  <update id="updateByPrimaryKeySelective" parameterType="com.chinasofti.rcloud.domain.AuditLogEntity" >
    <!--
      WARNING - @mbggenerated
      This element is automatically generated by MyBatis Generator, do not modify.
      This element was generated on Mon Jan 19 10:09:58 CST 2015.
    -->
    update boss_audit_log
    <set >
      <if test="userId != null" >
        user_id = #{userId,jdbcType=VARCHAR},
      </if>
      <if test="serviceId != null" >
        service_id = #{serviceId,jdbcType=VARCHAR},
      </if>
      <if test="userType != null" >
        user_type = #{userType,jdbcType=INTEGER},
      </if>
      <if test="roleCode != null" >
        role_code = #{roleCode,jdbcType=VARCHAR},
      </if>
      <if test="createDate != null" >
        create_date = #{createDate,jdbcType=TIMESTAMP},
      </if>
      <if test="operation != null" >
        operation = #{operation,jdbcType=VARCHAR},
      </if>
      <if test="remarks != null" >
        remarks = #{remarks,jdbcType=VARCHAR},
      </if>
      <if test="description != null" >
        description = #{description,jdbcType=VARCHAR},
      </if>
    </set>
    where audit_log_id = #{auditLogId,jdbcType=VARCHAR}
  </update>
  <update id="updateByPrimaryKey" parameterType="com.chinasofti.rcloud.domain.AuditLogEntity" >
    <!--
      WARNING - @mbggenerated
      This element is automatically generated by MyBatis Generator, do not modify.
      This element was generated on Mon Jan 19 10:09:58 CST 2015.
    -->
    update boss_audit_log
    set user_id = #{userId,jdbcType=VARCHAR},
      service_id = #{serviceId,jdbcType=VARCHAR},
      user_type = #{userType,jdbcType=INTEGER},
      role_code = #{roleCode,jdbcType=VARCHAR},
      create_date = #{createDate,jdbcType=TIMESTAMP},
      operation = #{operation,jdbcType=VARCHAR},
      remarks = #{remarks,jdbcType=VARCHAR},
      description = #{description,jdbcType=VARCHAR}
    where audit_log_id = #{auditLogId,jdbcType=VARCHAR}
  </update>
</mapper>